yunyun.py
yunyundb-0.3.0.dist-info/LICENSE
yunyundb-0.3.0.dist-info/METADATA
yunyundb-0.3.0.dist-info/WHEEL
yunyundb-0.3.0.dist-info/top_level.txt
yunyundb-0.3.0.dist-info/RECORD
